[
  {
    "turn": 1,
    "active_pokemon": {
      "p1a": "Chien-Pao",
      "p1b": "Rillaboom",
      "p2a": "Pelipper",
      "p2b": "Calyrex-Ice"
    },
    "moves": [
      [
        "p1b: Rillaboom",
        "Fake Out",
        [
          "p2b: Calyrex"
        ]
      ],
      [
        "p1a: Chien-Pao",
        "Icicle Crash",
        [
          "p2a: Raging Bolt"
        ]
      ]
    ],
    "hp": {
      "p1a": "100/100",
      "p1b": "100/100",
      "p2a": "0 fnt",
      "p2b": "94/100"
    },
    "field_effects": {
      "universal": [
        "Grassy Terrain"
      ],
      "p1-side": [],
      "p2-side": [],
      "spikes": {
        "p1": 0,
        "p2": 0
      }
    },
    "stat_changes": {},
    "status_conditions": {},
    "item_activations": [],
    "ability_activations": [],
    "move_failures": [],
    "critical_hits": [],
    "move_effectiveness": [
      [
        "p2a: Raging Bolt",
        "super effective"
      ]
    ],
    "missed_attacks": [],
    "self_inflicted_damage": [],
    "end_of_turn_effects": [],
    "tera_types": {},
    "abilities": {
      "p1a": "Sword of Ruin",
      "p1b": "Overgrow",
      "p2a": "Keen Eye",
      "p2b": "Unnerve"
    }
  },
  {
    "turn": 2,
    "active_pokemon": {
      "p1a": "Chien-Pao",
      "p1b": "Kyogre",
      "p2a": "Pelipper",
      "p2b": "Calyrex-Ice"
    },
    "moves": [
      [
        "p1a: Chien-Pao",
        "Icicle Crash",
        [
          "p2b: Calyrex"
        ]
      ],
      [
        "p1b: Rillaboom",
        "Wood Hammer",
        [
          "p2b: Calyrex"
        ]
      ],
      [
        "p2a: Pelipper",
        "Tailwind",
        [
          "p2a: Pelipper"
        ]
      ],
      [
        "p2b: Calyrex",
        "Glacial Lance",
        [
          "p1b: Rillaboom"
        ]
      ]
    ],
    "hp": {
      "p1a": "70/100",
      "p1b": "0 fnt",
      "p2a": "0 fnt",
      "p2b": "24/100"
    },
    "field_effects": {
      "universal": [
        "Grassy Terrain"
      ],
      "p1-side": [],
      "p2-side": [],
      "spikes": {
        "p1": 0,
        "p2": 0
      }
    },
    "stat_changes": {
      "p2b: Calyrex": {
        "atk": 2
      }
    },
    "status_conditions": {},
    "item_activations": [],
    "ability_activations": [
      [
        "p2b: Calyrex",
        "Chilling Neigh"
      ]
    ],
    "move_failures": [],
    "critical_hits": [],
    "move_effectiveness": [
      [
        "p2b: Calyrex",
        "resisted"
      ],
      [
        "p2b: Calyrex",
        "resisted"
      ],
      [
        "p1a: Chien-Pao",
        "resisted"
      ],
      [
        "p1b: Rillaboom",
        "super effective"
      ]
    ],
    "missed_attacks": [],
    "self_inflicted_damage": [],
    "end_of_turn_effects": [],
    "tera_types": {
      "p1b": "Grass",
      "p2b": "Fire"
    },
    "abilities": {
      "p1a": "Sword of Ruin",
      "p1b": "Drizzle",
      "p2a": "Keen Eye",
      "p2b": "Chilling Neigh"
    }
  },
  {
    "turn": 3,
    "active_pokemon": {
      "p1a": "Chien-Pao",
      "p1b": "Pachirisu",
      "p2a": "Pelipper",
      "p2b": "Calyrex-Ice"
    },
    "moves": [
      [
        "p2a: Pelipper",
        "Weather Ball",
        [
          "p1a: Chien-Pao"
        ]
      ],
      [
        "p2b: Calyrex",
        "Seed Bomb",
        [
          "p1b: Kyogre"
        ]
      ]
    ],
    "hp": {
      "p1a": "0 fnt",
      "p1b": "0 fnt",
      "p2a": "0 fnt",
      "p2b": "30/100"
    },
    "field_effects": {
      "universal": [
        "Grassy Terrain"
      ],
      "p1-side": [],
      "p2-side": [],
      "spikes": {
        "p1": 0,
        "p2": 0
      }
    },
    "stat_changes": {
      "p2b: Calyrex": {
        "atk": 2
      }
    },
    "status_conditions": {},
    "item_activations": [],
    "ability_activations": [
      [
        "p2b: Calyrex",
        "Chilling Neigh"
      ]
    ],
    "move_failures": [],
    "critical_hits": [],
    "move_effectiveness": [
      [
        "p1b: Kyogre",
        "super effective"
      ]
    ],
    "missed_attacks": [],
    "self_inflicted_damage": [],
    "end_of_turn_effects": [],
    "tera_types": {
      "p1b": "Grass",
      "p2b": "Fire"
    },
    "abilities": {
      "p1a": "Sword of Ruin",
      "p1b": "Run Away",
      "p2a": "Keen Eye",
      "p2b": "Chilling Neigh"
    }
  },
  {
    "turn": 4,
    "active_pokemon": {
      "p1a": "Chien-Pao",
      "p1b": "Pachirisu",
      "p2a": "Pelipper",
      "p2b": "Calyrex-Ice"
    },
    "moves": [],
    "hp": {
      "p1a": "0 fnt",
      "p1b": "0 fnt",
      "p2a": "0 fnt",
      "p2b": "30/100"
    },
    "field_effects": {
      "universal": [
        "Grassy Terrain"
      ],
      "p1-side": [],
      "p2-side": [],
      "spikes": {
        "p1": 0,
        "p2": 0
      }
    },
    "stat_changes": {
      "p2b: Calyrex": {
        "atk": 2
      }
    },
    "status_conditions": {},
    "item_activations": [],
    "ability_activations": [],
    "move_failures": [],
    "critical_hits": [],
    "move_effectiveness": [],
    "missed_attacks": [],
    "self_inflicted_damage": [],
    "end_of_turn_effects": [],
    "tera_types": {
      "p1b": "Grass",
      "p2b": "Fire"
    },
    "abilities": {
      "p1a": "Sword of Ruin",
      "p1b": "Run Away",
      "p2a": "Keen Eye",
      "p2b": "Chilling Neigh"
    }
  }
]