[
  {
    "turn": 1,
    "active_pokemon": {
      "p1a": "Kleavor",
      "p1b": "Mienshao",
      "p2a": "Zamazenta-Crowned",
      "p2b": "Urshifu"
    },
    "moves": [
      [
        "p2b: Urshifu",
        "Wicked Blow",
        [
          "p1b: Mienshao"
        ]
      ],
      [
        "p1a: Kleavor",
        "Tailwind",
        [
          "p1a: Kleavor"
        ]
      ]
    ],
    "hp": {
      "p1a": "100/100",
      "p1b": "41/100",
      "p2a": "100/100",
      "p2b": "100/100"
    },
    "field_effects": {
      "universal": [],
      "p1-side": [],
      "p2-side": [],
      "spikes": {
        "p1": 0,
        "p2": 0
      }
    },
    "stat_changes": {
      "p2a: Zamazenta": {
        "def": 1
      }
    },
    "status_conditions": {},
    "item_activations": [],
    "ability_activations": [
      [
        "p2a: Zamazenta",
        "Dauntless Shield"
      ]
    ],
    "move_failures": [],
    "critical_hits": [
      "p1b: Mienshao"
    ],
    "move_effectiveness": [
      [
        "p1b: Mienshao",
        "resisted"
      ]
    ],
    "missed_attacks": [],
    "self_inflicted_damage": [],
    "end_of_turn_effects": [],
    "tera_types": {},
    "abilities": {
      "p1a": "Swarm",
      "p1b": "Inner Focus",
      "p2a": "Dauntless Shield",
      "p2b": "Unseen Fist"
    }
  },
  {
    "turn": 2,
    "active_pokemon": {
      "p1a": "Ursaluna-Bloodmoon",
      "p1b": "Kleavor",
      "p2a": "Zamazenta-Crowned",
      "p2b": "Urshifu"
    },
    "moves": [
      [
        "p2a: Zamazenta",
        "Protect",
        [
          "p2a: Zamazenta"
        ]
      ],
      [
        "p1b: Mienshao",
        "Close Combat",
        [
          "p2b: Urshifu"
        ]
      ],
      [
        "p2b: Urshifu",
        "Close Combat",
        [
          "p1b: Mienshao"
        ]
      ]
    ],
    "hp": {
      "p1a": "100/100",
      "p1b": "0 fnt",
      "p2a": "100/100",
      "p2b": "100/100"
    },
    "field_effects": {
      "universal": [],
      "p1-side": [],
      "p2-side": [],
      "spikes": {
        "p1": 0,
        "p2": 0
      }
    },
    "stat_changes": {
      "p2a: Zamazenta": {
        "def": 1
      },
      "p2b: Urshifu": {
        "def": -1,
        "spd": -1
      }
    },
    "status_conditions": {},
    "item_activations": [],
    "ability_activations": [],
    "move_failures": [],
    "critical_hits": [],
    "move_effectiveness": [],
    "missed_attacks": [],
    "self_inflicted_damage": [],
    "end_of_turn_effects": [],
    "tera_types": {
      "p2b": "Ghost"
    },
    "abilities": {
      "p1a": "none",
      "p1b": "Swarm",
      "p2a": "Dauntless Shield",
      "p2b": "Unseen Fist"
    }
  },
  {
    "turn": 3,
    "active_pokemon": {
      "p1a": "Ursaluna-Bloodmoon",
      "p1b": "Kleavor",
      "p2a": "Raging Bolt",
      "p2b": "Chien-Pao"
    },
    "moves": [
      [
        "p1a: Ursaluna",
        "Earth Power",
        [
          "p2a: Raging Bolt"
        ]
      ],
      [
        "p1b: Kleavor",
        "Stone Axe",
        [
          "p2b: Chien-Pao"
        ]
      ]
    ],
    "hp": {
      "p1a": "91/100",
      "p1b": "0 fnt",
      "p2a": "31/100",
      "p2b": "1/100"
    },
    "field_effects": {
      "universal": [],
      "p1-side": [],
      "p2-side": [],
      "spikes": {
        "p1": 0,
        "p2": 0
      }
    },
    "stat_changes": {
      "p2a: Zamazenta": {
        "def": 1
      },
      "p2b: Urshifu": {
        "def": -1,
        "spd": -1
      }
    },
    "status_conditions": {},
    "item_activations": [],
    "ability_activations": [
      [
        "p2b: Chien-Pao",
        "Sword of Ruin"
      ]
    ],
    "move_failures": [],
    "critical_hits": [],
    "move_effectiveness": [
      [
        "p2a: Raging Bolt",
        "super effective"
      ],
      [
        "p2b: Chien-Pao",
        "super effective"
      ]
    ],
    "missed_attacks": [],
    "self_inflicted_damage": [],
    "end_of_turn_effects": [],
    "tera_types": {
      "p2b": "Ghost"
    },
    "abilities": {
      "p1a": "none",
      "p1b": "Swarm",
      "p2a": "none",
      "p2b": "Sword of Ruin"
    }
  },
  {
    "turn": 4,
    "active_pokemon": {
      "p1a": "Ursaluna-Bloodmoon",
      "p1b": "Kleavor",
      "p2a": "Raging Bolt",
      "p2b": "Chien-Pao"
    },
    "moves": [
      [
        "p1b: Kleavor",
        "Protect",
        [
          "p1b: Kleavor"
        ]
      ],
      [
        "p2b: Chien-Pao",
        "Protect",
        [
          "p2b: Chien-Pao"
        ]
      ],
      [
        "p2a: Raging Bolt",
        "Thunderclap",
        [
          ""
        ]
      ],
      [
        "p1a: Ursaluna",
        "Hyper Voice",
        [
          "p2b: Chien-Pao"
        ]
      ]
    ],
    "hp": {
      "p1a": "81/100",
      "p1b": "0 fnt",
      "p2a": "6/100",
      "p2b": "1/100"
    },
    "field_effects": {
      "universal": [],
      "p1-side": [],
      "p2-side": [],
      "spikes": {
        "p1": 0,
        "p2": 0
      }
    },
    "stat_changes": {
      "p2a: Zamazenta": {
        "def": 1
      },
      "p2b: Urshifu": {
        "def": -1,
        "spd": -1
      }
    },
    "status_conditions": {},
    "item_activations": [],
    "ability_activations": [],
    "move_failures": [
      "p2a: Raging Bolt"
    ],
    "critical_hits": [],
    "move_effectiveness": [],
    "missed_attacks": [],
    "self_inflicted_damage": [],
    "end_of_turn_effects": [],
    "tera_types": {
      "p2b": "Ghost"
    },
    "abilities": {
      "p1a": "none",
      "p1b": "Swarm",
      "p2a": "none",
      "p2b": "Sword of Ruin"
    }
  },
  {
    "turn": 5,
    "active_pokemon": {
      "p1a": "Ursaluna-Bloodmoon",
      "p1b": "Kleavor",
      "p2a": "Urshifu",
      "p2b": "Zamazenta-Crowned"
    },
    "moves": [
      [
        "p2a: Raging Bolt",
        "Thunderclap",
        [
          ""
        ]
      ],
      [
        "p2b: Chien-Pao",
        "Ice Spinner",
        [
          "p1b: Kleavor"
        ]
      ],
      [
        "p1a: Ursaluna",
        "Hyper Voice",
        [
          "p2a: Raging Bolt"
        ]
      ],
      [
        "p1b: Kleavor",
        "Tailwind",
        [
          "p1b: Kleavor"
        ]
      ]
    ],
    "hp": {
      "p1a": "72/100",
      "p1b": "46/100",
      "p2a": "88/100",
      "p2b": "98/100"
    },
    "field_effects": {
      "universal": [],
      "p1-side": [],
      "p2-side": [],
      "spikes": {
        "p1": 0,
        "p2": 0
      }
    },
    "stat_changes": {
      "p2a: Zamazenta": {
        "def": 1
      },
      "p2b: Urshifu": {
        "def": -1,
        "spd": -1
      }
    },
    "status_conditions": {},
    "item_activations": [],
    "ability_activations": [],
    "move_failures": [
      "p2a: Raging Bolt"
    ],
    "critical_hits": [],
    "move_effectiveness": [],
    "missed_attacks": [],
    "self_inflicted_damage": [],
    "end_of_turn_effects": [],
    "tera_types": {
      "p2b": "Ghost"
    },
    "abilities": {
      "p1a": "none",
      "p1b": "Swarm",
      "p2a": "Unseen Fist",
      "p2b": "none"
    }
  },
  {
    "turn": 6,
    "active_pokemon": {
      "p1a": "Ursaluna-Bloodmoon",
      "p1b": "Kleavor",
      "p2a": "Urshifu",
      "p2b": "Zamazenta-Crowned"
    },
    "moves": [
      [
        "p2b: Zamazenta",
        "Protect",
        [
          "p2b: Zamazenta"
        ]
      ],
      [
        "p1a: Ursaluna",
        "Blood Moon",
        [
          "p2a: Urshifu"
        ]
      ],
      [
        "p1b: Kleavor",
        "X-Scissor",
        [
          "p2b: Zamazenta"
        ]
      ]
    ],
    "hp": {
      "p1a": "62/100",
      "p1b": "46/100",
      "p2a": "0 fnt",
      "p2b": "98/100"
    },
    "field_effects": {
      "universal": [],
      "p1-side": [],
      "p2-side": [],
      "spikes": {
        "p1": 0,
        "p2": 0
      }
    },
    "stat_changes": {
      "p2a: Zamazenta": {
        "def": 1
      },
      "p2b: Urshifu": {
        "def": -1,
        "spd": -1
      }
    },
    "status_conditions": {},
    "item_activations": [],
    "ability_activations": [],
    "move_failures": [],
    "critical_hits": [],
    "move_effectiveness": [],
    "missed_attacks": [],
    "self_inflicted_damage": [],
    "end_of_turn_effects": [],
    "tera_types": {
      "p2b": "Ghost"
    },
    "abilities": {
      "p1a": "none",
      "p1b": "Swarm",
      "p2a": "Unseen Fist",
      "p2b": "none"
    }
  },
  {
    "turn": 7,
    "active_pokemon": {
      "p1a": "Ursaluna-Bloodmoon",
      "p1b": "Kleavor",
      "p2a": "Urshifu",
      "p2b": "Zamazenta-Crowned"
    },
    "moves": [],
    "hp": {
      "p1a": "62/100",
      "p1b": "46/100",
      "p2a": "0 fnt",
      "p2b": "98/100"
    },
    "field_effects": {
      "universal": [],
      "p1-side": [],
      "p2-side": [],
      "spikes": {
        "p1": 0,
        "p2": 0
      }
    },
    "stat_changes": {
      "p2a: Zamazenta": {
        "def": 1
      },
      "p2b: Urshifu": {
        "def": -1,
        "spd": -1
      }
    },
    "status_conditions": {},
    "item_activations": [],
    "ability_activations": [],
    "move_failures": [],
    "critical_hits": [],
    "move_effectiveness": [],
    "missed_attacks": [],
    "self_inflicted_damage": [],
    "end_of_turn_effects": [],
    "tera_types": {
      "p2b": "Ghost"
    },
    "abilities": {
      "p1a": "none",
      "p1b": "Swarm",
      "p2a": "Unseen Fist",
      "p2b": "none"
    }
  }
]